[
  {"name": "Marvel's Spider-Man Remastered", "platform": "PS5", "trophies": "79", "difficulty": "3.37", "time": "24 дня", "color": "#c0392b"},
  {"name": "LEGO Marvel Super Heroes 2", "platform": "PS4", "trophies": "76", "difficulty": "2.45", "time": "127 дней", "color": "#e74c3c"},
  {"name": "One Piece: Pirate Warriors 4", "platform": "PS4", "trophies": "40", "difficulty": "3.33", "time": "127 дней", "color": "#8e44ad"},
  {"name": "Stick Fight: The Game", "platform": "PS4", "trophies": "28", "difficulty": "2.45", "time": "3 дня", "color": "#f39c12"},
  {"name": "Ghost of Tsushima: Director's Cut", "platform": "PS5", "trophies": "77", "difficulty": "3.15", "time": "?", "color": "#2ecc71"},
  {"name": "Marvel’s Spider-Man 2", "platform": "PS5", "trophies": "43", "difficulty": "2.50", "time": "?", "color": "#e74c3c"},
  {"name": "Call of Duty: Modern Warfare 2 Campaign Remastered", "platform": "PS4", "trophies": "51", "difficulty": "4.60", "time": "9 дней", "color": "#34495e"},
  {"name": "Middle-earth: Shadow of Mordor - Game of the Year Edition", "platform": "PS4", "trophies": "51", "difficulty": "3.90", "time": "?", "color": "#7f8c8d"},
  {"name": "Ratchet & Clank: Rift Apart", "platform": "PS5", "trophies": "37", "difficulty": "2.80", "time": "?", "color": "#3498db"},
  {"name": "inFAMOUS: First Light", "platform": "PS4", "trophies": "14", "difficulty": "2.40", "time": "?", "color": "#e67e22"},
  {"name": "Astro's Playroom", "platform": "PS5", "trophies": "43", "difficulty": "1.50", "time": "?", "color": "#1abc9c"},
  {"name": "LEGO Marvel Super Heroes", "platform": "PS4", "trophies": "46", "difficulty": "2.30", "time": "?", "color": "#e74c3c"},
  {"name": "Prototype 2", "platform": "PS4", "trophies": "44", "difficulty": "4.10", "time": "?", "color": "#c0392b"},
  {"name": "Deponia", "platform": "PS4", "trophies": "27", "difficulty": "1.80", "time": "?", "color": "#f1c40f"},
  {"name": "Marvel’s Spider-Man: Miles Morales", "platform": "PS5", "trophies": "50", "difficulty": "2.20", "time": "?", "color": "#e74c3c"},
  {"name": "Naruto Shippuden: Ultimate Ninja Storm 2", "platform": "PS4", "trophies": "42", "difficulty": "3.50", "time": "?", "color": "#e67e22"},
  {"name": "Ratchet & Clank", "platform": "PS4", "trophies": "37", "difficulty": "2.50", "time": "?", "color": "#3498db"},
  {"name": "A Way Out", "platform": "PS4", "trophies": "15", "difficulty": "2.10", "time": "?", "color": "#2c3e50"},
  {"name": "Concrete Genie", "platform": "PS4", "trophies": "23", "difficulty": "1.60", "time": "?", "color": "#9b59b6"},
  {"name": "Hotline Miami", "platform": "PS4", "trophies": "29", "difficulty": "5.80", "time": "?", "color": "#e74c3c"},
  {"name": "Far Cry 3 Classic Edition", "platform": "PS4", "trophies": "44", "difficulty": "3.10", "time": "?", "color": "#f39c12"},
  {"name": "Metro: Last Light Redux", "platform": "PS4", "trophies": "50", "difficulty": "4.30", "time": "?", "color": "#34495e"},
  {"name": "Metro 2033 Redux", "platform": "PS4", "trophies": "50", "difficulty": "4.20", "time": "?", "color": "#34495e"},
  {"name": "Uncharted: The Lost Legacy", "platform": "PS4", "trophies": "50", "difficulty": "3.40", "time": "?", "color": "#1abc9c"},
  {"name": "LEGO Marvel's Avengers", "platform": "PS4", "trophies": "51", "difficulty": "2.20", "time": "?", "color": "#e74c3c"},
  {"name": "Psychonauts", "platform": "PS4", "trophies": "38", "difficulty": "3.50", "time": "?", "color": "#8e44ad"},
  {"name": "Uncharted 3: Drake’s Deception Remastered", "platform": "PS4", "trophies": "53", "difficulty": "3.60", "time": "?", "color": "#1abc9c"},
  {"name": "Uncharted: Drake’s Fortune Remastered", "platform": "PS4", "trophies": "48", "difficulty": "3.20", "time": "?", "color": "#1abc9c"},
  {"name": "Sleeping Dogs: Definitive Edition", "platform": "PS4", "trophies": "51", "difficulty": "3.80", "time": "?", "color": "#e74c3c"},
  {"name": "God of War III: Remastered", "platform": "PS4", "trophies": "35", "difficulty": "4.00", "time": "?", "color": "#c0392b"},
  {"name": "I Am The Hero", "platform": "PS4", "trophies": "19", "difficulty": "2.00", "time": "?", "color": "#f39c12"},
  {"name": "NARUTO SHIPPUDEN: Ultimate Ninja STORM 3 Full Burst", "platform": "PS4", "trophies": "50", "difficulty": "3.70", "time": "?", "color": "#e67e22"},
  {"name": "Uncharted 2: Among Thieves Remastered", "platform": "PS4", "trophies": "48", "difficulty": "3.30", "time": "?", "color": "#1abc9c"},
  {"name": "NARUTO: Ultimate Ninja STORM", "platform": "PS4", "trophies": "42", "difficulty": "3.40", "time": "?", "color": "#e67e22"},
  {"name": "Horizon Chase Turbo", "platform": "PS4", "trophies": "31", "difficulty": "3.90", "time": "?", "color": "#f1c40f"},
  {"name": "Detroit: Become Human", "platform": "PS4", "trophies": "49", "difficulty": "2.10", "time": "?", "color": "#3498db"},
  {"name": "Heavy Rain", "platform": "PS4", "trophies": "57", "difficulty": "2.90", "time": "?", "color": "#2c3e50"},
  {"name": "Assassin's Creed Syndicate", "platform": "PS4", "trophies": "50", "difficulty": "3.00", "time": "?", "color": "#f39c12"},
  {"name": "Batman: Arkham Knight", "platform": "PS4", "trophies": "66", "difficulty": "4.50", "time": "?", "color": "#2c5282"},
  {"name": "God of War", "platform": "PS4", "trophies": "37", "difficulty": "3.60", "time": "?", "color": "#c0392b"},
  {"name": "Assassin's Creed Origins", "platform": "PS4", "trophies": "51", "difficulty": "3.20", "time": "?", "color": "#f39c12"},
  {"name": "Assassin's Creed Revelations HD", "platform": "PS4", "trophies": "50", "difficulty": "3.50", "time": "?", "color": "#f39c12"},
  {"name": "Assassin's Creed Brotherhood HD", "platform": "PS4", "trophies": "51", "difficulty": "3.40", "time": "?", "color": "#f39c12"},
  {"name": "Assassin's Creed II HD", "platform": "PS4", "trophies": "51", "difficulty": "2.80", "time": "?", "color": "#f39c12"},
  {"name": "Uncharted 4: A Thief's End", "platform": "PS4", "trophies": "56", "difficulty": "3.50", "time": "?", "color": "#1abc9c"},
  {"name": "Middle-earth: Shadow of War", "platform": "PS4", "trophies": "53", "difficulty": "3.80", "time": "?", "color": "#7f8c8d"},
  {"name": "Watch Dogs 2", "platform": "PS4", "trophies": "50", "difficulty": "2.90", "time": "?", "color": "#3498db"},
  {"name": "Bully", "platform": "PS4", "trophies": "39", "difficulty": "3.00", "time": "?", "color": "#f1c40f"},
  {"name": "Call of Duty: Modern Warfare Remastered", "platform": "PS4", "trophies": "51", "difficulty": "4.40", "time": "?", "color": "#34495e"},
  {"name": "Marvel's Spider-Man", "platform": "PS4", "trophies": "51", "difficulty": "2.70", "time": "?", "color": "#c0392b"},
  {"name": "Naruto Shippuden: Ultimate Ninja Storm 4", "platform": "PS4", "trophies": "50", "difficulty": "3.50", "time": "?", "color": "#e67e22"},
  {"name": "inFAMOUS Second Son", "platform": "PS4", "trophies": "48", "difficulty": "2.80", "time": "?", "color": "#e67e22"},
  {"name": "Until Dawn 2015", "platform": "PS4", "trophies": "19", "difficulty": "2.30", "time": "?", "color": "#2c3e50"},
  {"name": "Batman: Return to Arkham - Arkham Asylum", "platform": "PS4", "trophies": "48", "difficulty": "5.67", "time": "1 535 дней", "color": "#2c5282"},
  {"name": "Cairn", "platform": "PS5", "trophies": "53", "difficulty": "—", "time": "5 дней", "color": "#276749"},
  {"name": "Crysis Remastered", "platform": "PS4", "trophies": "41", "difficulty": "3.78", "time": "7 дней", "color": "#9b2c2c"},
  {"name": "Pinball Heroes", "platform": "PS5", "trophies": "21", "difficulty": "1.44", "time": "22 часа", "color": "#6b46c1"},
  {"name": "Twisted Metal 4", "platform": "PS5", "trophies": "21", "difficulty": "3.38", "time": "2 часа", "color": "#c05621"},
  {"name": "Twisted Metal III", "platform": "PS5", "trophies": "21", "difficulty": "3.00", "time": "3 дня", "color": "#2d3748"}
]
